bxlogs/__init__.py
bxlogs/py.typed
bxlogs-0.1.0.dist-info/LICENSE
bxlogs-0.1.0.dist-info/METADATA
bxlogs-0.1.0.dist-info/WHEEL
bxlogs-0.1.0.dist-info/RECORD
