Metadata-Version: 2.1
Name: bxlogs
Version: 0.1.0
Summary: simple logs config
Home-page: https://github.com/Bixoto/bxlogs
License: MIT
Author: Baptiste Fontaine
Author-email: baptiste@bixoto.com
Requires-Python: >=3.8,<4.0
Classifier: Development Status :: 5 - Production/Stable
Classifier: License :: OSI Approved :: MIT License
Classifier: Programming Language :: Python :: 3
Classifier: Programming Language :: Python :: 3.8
Classifier: Programming Language :: Python :: 3.9
Classifier: Programming Language :: Python :: 3.10
Classifier: Programming Language :: Python :: 3.11
